MANIFEST.in
README.md
requirements.txt
setup.py
docs/HISTORY.txt
wheelcms_rss/__init__.py
wheelcms_rss/feeds.py
wheelcms_rss/models.py
wheelcms_rss.egg-info/PKG-INFO
wheelcms_rss.egg-info/SOURCES.txt
wheelcms_rss.egg-info/dependency_links.txt
wheelcms_rss.egg-info/namespace_packages.txt
wheelcms_rss.egg-info/not-zip-safe
wheelcms_rss.egg-info/requires.txt
wheelcms_rss.egg-info/top_level.txt
wheelcms_rss/templates/wheelcms_rss/feedlinks.html
wheelcms_rss/tests/__init__.py
wheelcms_rss/tests/conftest.py
wheelcms_rss/tests/test_rss.py