Metadata-Version: 1.1
Name: wheelcms-rss
Version: 0.8.2
Summary: WheelCMS RSS feed generator
Home-page: http://github.com/wheelcms/wheelcms_rss
Author: Ivo van der Wijk
Author-email: wheelcms@in.m3r.nl
License: BSD
Platform: UNKNOWN
Classifier: Programming Language :: Python
